bartab_core/__init__.py
bartab_core/address_validation.py
bartab_core/api_config.py
bartab_core/apps.py
bartab_core/cache_manager.py
bartab_core/date.py
bartab_core/display_value_validator.py
bartab_core/email.py
bartab_core/file.py
bartab_core/float.py
bartab_core/integer.py
bartab_core/json.py
bartab_core/jwt.py
bartab_core/lambda_client.py
bartab_core/list.py
bartab_core/microservice_clients.py
bartab_core/microservices.py
bartab_core/mocks.py
bartab_core/models.py
bartab_core/normalize.py
bartab_core/paths.py
bartab_core/permissions.py
bartab_core/phone_number.py
bartab_core/requests.py
bartab_core/secrets.py
bartab_core/serializers.py
bartab_core/string.py
bartab_core/test.py
bartab_core/time.py
bartab_core/url.py
bartab_core/user_info.py
bartab_core/validate.py
core_backend_bartab_utils-1.0.26.dist-info/LICENSE.txt
core_backend_bartab_utils-1.0.26.dist-info/METADATA
core_backend_bartab_utils-1.0.26.dist-info/WHEEL
core_backend_bartab_utils-1.0.26.dist-info/top_level.txt
core_backend_bartab_utils-1.0.26.dist-info/RECORD
